{
  "version": "0.4.1",
  "flags": {},
  "shapes": [
    {
      "label": "car",
      "text": "car",
      "points": [
        [
          0,
          319
        ],
        [
          173,
          426
        ]
      ],
      "group_id": null,
      "shape_type": "rectangle",
      "flags": {
        "category": "vehicle"
      }
    },
    {
      "label": "car",
      "text": "car",
      "points": [
        [
          188,
          249
        ],
        [
          339,
          395
        ]
      ],
      "group_id": null,
      "shape_type": "rectangle",
      "flags": {
        "category": "vehicle"
      }
    },
    {
      "label": "truck",
      "text": "truck",
      "points": [
        [
          302,
          14
        ],
        [
          600,
          351
        ]
      ],
      "group_id": null,
      "shape_type": "rectangle",
      "flags": {
        "category": "vehicle"
      }
    },
    {
      "label": "van",
      "text": "van",
      "points": [
        [
          731,
          94
        ],
        [
          1279,
          543
        ]
      ],
      "group_id": null,
      "shape_type": "rectangle",
      "flags": {
        "category": "vehicle"
      }
    },
    {
      "label": "car",
      "text": "car",
      "points": [
        [
          653,
          234
        ],
        [
          721,
          280
        ]
      ],
      "group_id": null,
      "shape_type": "rectangle",
      "flags": {
        "category": "vehicle"
      }
    }
  ],
  "imagePath": "D2_frame_0088.jpg",
  "imageData": null,
  "imageHeight": 544,
  "imageWidth": 1280
}